{
    "server": "irc.freenode.org",
    "nick": "mynick",
    "password": "mypassword",
    "showJoinMessages": false,
    "showPartMessages": false,
    "channels": {
        "irc.freenode.org": [
            "#testnanoirc",
            "#testnanoirc2"
        ],
        "irc.synirc.net": [
            "#testnanoirc",
            "#testnanoirc2"
        ]
    },
    "colors": {
        "timestamp": "yellow",
        "channel": "yellow",
        "user": "green",
        "mentions": "red"
    }
}

